{
  "openapi": "3.1.0",
  "info": {
    "version": "1.0"
  },
  "paths": {
    "/foo": {
      "post": {
        "parameters": [
          {
            "name": "Payload_complex",
            "in": "header",
            "description": "If a header uses nested structures, a requestbody is more appropriate.",
            "required": true,
            "schema": {
              "type": "object",
              "properties": {
                "nestedfield": {
                  "type": "string"
                }
              }
            }
          }
        ]
      }
    }
  }
}
